{
 "actions": [],
 "allow_rename": 1,
 "creation": "2025-09-16 18:33:27.712907",
 "custom": 1,
 "doctype": "DocType",
 "editable_grid": 1,
 "engine": "InnoDB",
 "field_order": [
  "basics_section",
  "include"
 ],
 "fields": [
  {
   "fieldname": "basics_section",
   "fieldtype": "Section Break",
   "label": "basics"
  },
  {
   "default": "-",
   "description": "What's included in the tour",
   "fieldname": "include",
   "fieldtype": "Data",
   "in_filter": 1,
   "in_list_view": 1,
   "in_preview": 1,
   "in_standard_filter": 1,
   "label": "include",
   "reqd": 1
  }
 ],
 "grid_page_length": 50,
 "index_web_pages_for_search": 1,
 "istable": 1,
 "links": [],
 "modified": "2025-09-16 18:37:44.736143",
 "modified_by": "Administrator",
 "module": "Tours",
 "name": "Tour Inclusion",
 "owner": "Administrator",
 "permissions": [],
 "row_format": "Dynamic",
 "sort_field": "modified",
 "sort_order": "DESC",
 "states": []
}